README.md
setup.cfg
setup.py
bin/hackthebox.py
hackthebox_api.egg-info/PKG-INFO
hackthebox_api.egg-info/SOURCES.txt
hackthebox_api.egg-info/dependency_links.txt
hackthebox_api.egg-info/requires.txt
hackthebox_api.egg-info/top_level.txt
htb/__init__.py
htb/api.py
htb/challenges.py
htb/cli.py
htb/colorize.py
htb/exceptions.py
htb/machines.py
htb/pusher.py
htb/shoutbox.py
htb/views.py